{"type": "Feature", "id": 12515174, "geometry": {"type": "Point", "coordinates": [175.024506, -39.96059]}, "properties": {"woe:id": 12515174, "woe:parent_id": 28644014, "woe:name": "Wanganui Airport", "woe:placetype": 14, "woe:placetype_name": "Airport", "woe:lang": "ENG", "iso:country": "NZ", "meta:provider": ["geoplanet:7.3.1", "geoplanet:7.3.2", "geoplanet:7.4.0", "geoplanet:7.4.1", "geoplanet:7.5.1", "geoplanet:7.5.2", "geoplanet:7.6.0", "geoplanet:7.8.1", "geoplanet:7.9.0", "geoplanet:7.10.0", "geoplanet:8.0.0", "woeplanet:8.0.0"], "meta:indexed": "2020-08-20T20:19:29.705127", "woe:alias_ENG_V": ["WAG", "WAG Airport"], "meta:updated": "2020-10-14T11:34:30.904196", "woe:hierarchy": {"continent": 24865674, "country": 23424916, "town": 0, "planet": 1, "county": 55875908, "suburb": 0, "state": 15021764, "region": 0, "localadmin": 0}, "woe:timezone_id": 28350937, "woe:hash": "rbukwv2uww4g", "woe:centroid": [175.024506, -39.96059], "geom:latitude": -39.96059, "geom:longitude": 175.024506, "geom:hash": "rbukwv2uww4g", "woe:latitude": -39.96059, "geom:centroid": [175.024506, -39.96059], "woe:longitude": 175.024506, "woe:repo": "woeplanet-airport-nz", "geom:area": 0.0, "woe:scale": 19}}