{"type": "Feature", "id": 12523364, "geometry": {"type": "Point", "coordinates": [174.082413, -35.284649]}, "properties": {"woe:id": 12523364, "woe:parent_id": 2350008, "woe:name": "Paihia Airport", "woe:placetype": 14, "woe:placetype_name": "Airport", "woe:lang": "ENG", "iso:country": "NZ", "meta:provider": ["geoplanet:7.3.1", "geoplanet:7.3.2", "geoplanet:7.4.0", "geoplanet:7.4.1", "geoplanet:7.5.1", "geoplanet:7.5.2", "geoplanet:7.6.0", "geoplanet:7.8.1", "geoplanet:7.9.0", "geoplanet:7.10.0", "geoplanet:8.0.0", "woeplanet:8.0.0"], "meta:indexed": "2020-08-20T20:19:29.665516", "woe:alias_ENG_V": ["PIJ", "PIJ Airport"], "meta:updated": "2020-10-14T11:34:30.885224", "woe:hierarchy": {"continent": 24865674, "country": 23424916, "town": 0, "planet": 1, "county": 55875844, "suburb": 0, "state": 15021755, "region": 0, "localadmin": 0}, "woe:timezone_id": 28350937, "woe:hash": "rcez32dun0xq", "woe:centroid": [174.082413, -35.284649], "geom:latitude": -35.284649, "geom:longitude": 174.082413, "geom:hash": "rcez32dun0xq", "woe:latitude": -35.284649, "geom:centroid": [174.082413, -35.284649], "woe:longitude": 174.082413, "woe:repo": "woeplanet-airport-nz", "geom:area": 0.0, "woe:scale": 19}}