{"type": "Feature", "id": 28677841, "geometry": {"type": "Point", "coordinates": [175.257004, -38.83868]}, "properties": {"woe:id": 28677841, "woe:parent_id": 2350729, "woe:name": "Taumarunui Aerodrome", "woe:placetype": 14, "woe:placetype_name": "Airport", "woe:lang": "ENG", "iso:country": "NZ", "meta:provider": ["geoplanet:7.3.1", "geoplanet:7.3.2", "geoplanet:7.4.0", "geoplanet:7.4.1", "geoplanet:7.5.1", "geoplanet:7.5.2", "geoplanet:7.6.0", "geoplanet:7.8.1", "geoplanet:7.9.0", "geoplanet:7.10.0", "geoplanet:8.0.0", "woeplanet:8.0.0"], "meta:indexed": "2020-08-20T20:19:29.681631", "meta:updated": "2020-10-14T11:34:30.863270", "woe:hierarchy": {"continent": 24865674, "country": 23424916, "town": 0, "planet": 1, "county": 55875920, "suburb": 0, "state": 15021764, "region": 0, "localadmin": 0}, "woe:timezone_id": 28350937, "woe:hash": "rcheh1dk21mc", "woe:centroid": [175.257004, -38.83868], "geom:latitude": -38.83868, "geom:longitude": 175.257004, "geom:hash": "rcheh1dk21mc", "woe:latitude": -38.83868, "geom:centroid": [175.257004, -38.83868], "woe:longitude": 175.257004, "woe:repo": "woeplanet-airport-nz", "geom:area": 0.0, "woe:scale": 19}}