{"type": "Feature", "id": 12515172, "properties": {"woe:id": 12515172, "woe:parent_id": 28643957, "woe:name": "Wairoa Airport", "woe:placetype": 14, "woe:placetype_name": "Airport", "woe:lang": "ENG", "iso:country": "NZ", "meta:provider": ["geoplanet:7.3.1", "geoplanet:7.3.2", "geoplanet:7.4.0", "geoplanet:7.4.1", "geoplanet:7.5.1", "geoplanet:7.5.2", "geoplanet:7.6.0", "geoplanet:7.8.1", "geoplanet:7.9.0", "geoplanet:7.10.0", "geoplanet:8.0.0", "woeplanet:8.0.0"], "meta:indexed": "2020-08-20T20:19:29.652545", "woe:alias_ENG_V": ["Wairoa Aerodrome"], "meta:updated": "2020-08-22T02:50:23.799084", "woe:hierarchy": {"continent": 24865674, "country": 23424916, "town": 0, "planet": 1, "county": 55875883, "suburb": 0, "state": 15021760, "region": 0, "localadmin": 0}, "woe:timezone_id": 28350937, "woe:hash": "rcn4j12e9v32", "woe:centroid": [177.40799, -39.015942], "geom:latitude": -39.015942, "geom:longitude": 177.40799, "geom:hash": "rcn4j12e9v32", "woe:latitude": -39.015942, "geom:centroid": [177.40799, -39.015942], "woe:longitude": 177.40799, "woe:repo": "woeplanet-airport-nz"}, "geometry": {"coordinates": [177.40799, -39.015942], "type": "Point"}}